setup.py
src/speakin_voice_sdk/__init__.py
src/speakin_voice_sdk/api.py
src/speakin_voice_sdk/api_obj.py
src/speakin_voice_sdk/base.py
src/speakin_voice_sdk/const.py
src/speakin_voice_sdk/session_api.py
src/speakin_voice_sdk/session_api_obj.py
src/speakin_voice_sdk/user_api.py
src/speakin_voice_sdk/user_api_obj.py
src/speakin_voice_sdk/util.py
src/speakin_voice_sdk.egg-info/PKG-INFO
src/speakin_voice_sdk.egg-info/SOURCES.txt
src/speakin_voice_sdk.egg-info/dependency_links.txt
src/speakin_voice_sdk.egg-info/requires.txt
src/speakin_voice_sdk.egg-info/top_level.txt