Metadata-Version: 1.0
Name: speakin-voice-sdk
Version: 1.0.1
Summary: speakin voice sdk
Home-page: http://www.speakin.mobi/pages/index.html
Author: panleiming
Author-email: panleiming@speakin.mobi
License: UNKNOWN
Platform: UNKNOWN
